plumes/__init__.py
plumes/cli.py
plumes/config.py
plumes/settings.toml
plumes/utilities.py
plumes-2.3.2.dist-info/entry_points.txt
plumes-2.3.2.dist-info/LICENSE
plumes-2.3.2.dist-info/WHEEL
plumes-2.3.2.dist-info/METADATA
plumes-2.3.2.dist-info/RECORD
