Metadata-Version: 2.1
Name: plumes
Version: 2.3.2
Summary: Simple Twitter CLI for day-to-day social media hygiene
Home-page: https://github.com/nnadeau/plumes
License: MIT
Keywords: twitter,cli,api,automation,cron
Author: Nicholas Nadeau
Author-email: nicholas.nadeau@gmail.com
Requires-Python: >=3.6.1,<4.0.0
Classifier: Development Status :: 5 - Production/Stable
Classifier: Intended Audience :: Developers
Classifier: Intended Audience :: Education
Classifier: Intended Audience :: End Users/Desktop
Classifier: Intended Audience :: Information Technology
Classifier: Intended Audience :: Other Audience
Classifier: Intended Audience :: Science/Research
Classifier: License :: OSI Approved :: MIT License
Classifier: Operating System :: MacOS
Classifier: Operating System :: Microsoft
Classifier: Operating System :: Microsoft :: Windows
Classifier: Operating System :: OS Independent
Classifier: Operating System :: POSIX
Classifier: Operating System :: POSIX :: Linux
Classifier: Programming Language :: Python
Classifier: Programming Language :: Python :: 3
Classifier: Programming Language :: Python :: 3 :: Only
Classifier: Programming Language :: Python :: 3.7
Classifier: Programming Language :: Python :: 3.8
Classifier: Programming Language :: Python :: Implementation :: CPython
Classifier: Topic :: Communications
Classifier: Topic :: Internet
Classifier: Topic :: Scientific/Engineering
Classifier: Topic :: Scientific/Engineering :: Artificial Intelligence
Requires-Dist: dynaconf (>=3.1.0,<4.0.0)
Requires-Dist: fire (>=0.3.1,<0.4.0)
Requires-Dist: python-box (>=5.1.0,<6.0.0)
Requires-Dist: toml (>=0.10.1,<0.11.0)
Requires-Dist: tqdm (>=4.48.2,<5.0.0)
Requires-Dist: tweepy (>=3.9.0,<4.0.0)
Project-URL: Documentation, https://github.com/nnadeau/plumes
Project-URL: Repository, https://github.com/nnadeau/plumes
